[
  {
    "strName" : "TIsCoffeeMachine",
    "strCondName" : "",
    "fChance"     : 1.0,
    "fCount"      : 1.0,
    "aReqs"         : [
      "IsCoffeeMachine"
    ],
    "aForbids"      : [
    ],
    "aTriggers"     : [
    ],
    "bAND"          : true
},
{
  "strName" : "TIsFanBreakoutWarriors",
  "strCondName" : "",
  "fChance"     : 1.0,
  "fCount"      : 1.0,
  "aReqs"         : [
    "IsFanBreakoutWarriors",
    "IsHuman"
  ],
  "aForbids"      : [
  ],
  "aTriggers"     : [
  ],
  "bAND"          : true
},
{
    "strName" : "TIsFanBreakoutShooters",
    "strCondName" : "",
    "fChance"     : 1.0,
    "fCount"      : 1.0,
    "aReqs"         : [
        "IsFanBreakoutShooters",
        "IsHuman"
    ],
    "aForbids"      : [
      ],
    "aTriggers"     : [
      ],
    "bAND"          : true
},
{
  "strName" : "TIsBOFan",
  "strCondName" : "",
  "fChance"     : 1.0,
  "fCount"      : 1.0,
  "aReqs"         : [
            "IsBOFan",
            "IsHuman"
          ],
  "aForbids"      : [
            ""
          ],
  "aTriggers"     : [
          ],
  "bAND"          : true
},
{
  "strName" : "TIsFanViceroys",
  "strCondName" : "",
  "fChance"     : 1.0,
  "fCount"      : 1.0,
  "aReqs"         : [
            "IsFanViceroys",
            "IsHuman"
          ],
  "aForbids"      : [
            "IsFanDamaskRose"
          ],
  "aTriggers"     : [
          ],
  "bAND"          : true
},
{
  "strName" : "TIsFanDamaskRose",
  "strCondName" : "",
  "fChance"     : 1.0,
  "fCount"      : 1.0,
  "aReqs"         : [
            "IsFanDamaskRose",
            "IsHuman"
          ],
  "aForbids"      : [
            "IsFanViceroys"
          ],
  "aTriggers"     : [
          ],
  "bAND"          : true
},
{
  "strName" : "TIsSeekAltruismUs",
  "fChance" : 0.5,
  "fCount"  : 0.0,
  "aReqs"   : [
    "IsKind",
    "IsSelfless"
  ],
  "aForbids" : [
    "IsApathetic",
    "IsCruel",
    "IsOblivious",
    "IsSelfish"
  ],
  "aTriggersForbid" :[
	"TNoDiscomfortsSocial"
  ],
  "bAND"     : false
},
{
  "strName" : "TIsSeekAltruismAllowUs",
  "fChance" : 0.5,
  "fCount"  : 0.0,
  "aReqs"   : [
    "IsHumble",
    "IsPushover",
    "IsQuitter",
    "IsSelfish"
  ],
  "aForbids" : [
    "IsAmbitious",
    "IsApathetic",
    "IsArrogant",
    "IsDiligent",
    "IsImpatient",
    "IsSelfless",
    "IsStubborn"
  ],
  "bAND"     : false
},
{
  "strName" : "TIsSeekAltruismDenyUs",
  "fChance" : 0.75,
  "fCount"  : 0.0,
  "aReqs"   : [
    "IsArrogant",
    "IsImpatient",
    "IsStubborn"
  ],
  "aForbids" : [
    "IsForgiving",
    "IsHumble",
    "IsKind",
    "IsPatient",
    "IsPushover",
    "IsQuitter",
    "IsShy"
  ],
  "bAND"     : false
},
{
  "strName" : "TIsSeekAltruismN3Us",
  "fChance" : 0.5,
  "fCount"  : 0.0,
  "aReqs"   : [
    "IsKind",
    "IsSelfless"
  ],
  "aForbids" : [
    "IsApathetic",
    "IsCruel",
    "IsOblivious",
    "IsSelfish"
  ],
  "aTriggersForbid" :[
	"TNoDiscomfortsSocial"
  ],
  "bAND"     : false
},
{
  "strName" : "TIsSeekAltruismN3AllowUs",
  "fChance" : 1.0,
  "fCount"  : 0.0,
  "aReqs"   : [
    "IsHumble",
    "IsPushover",
    "IsQuitter",
    "IsSelfish"
  ],
  "aForbids" : [
    "IsAmbitious",
    "IsApathetic",
    "IsArrogant",
    "IsDiligent",
    "IsImpatient",
    "IsSelfless",
    "IsStubborn"
  ],
  "bAND"     : false
},
{
  "strName" : "TIsSeekAltruismN3DenyUs",
  "fChance" : 1.0,
  "fCount"  : 0.0,
  "bAND"    : false
},
{
  "strName" : "TIsSeekAutonomyUs",
  "fChance" : 1.0,
  "fCount"  : 0.0,
  "aReqs"   : [
    "IsApathetic",
    "IsArrogant",
    "IsBrave",
    "IsGregarious",
    "IsStubborn"
  ],
  "aForbids" : [
    "IsComplacent",
    "IsCraven",
    "IsFollower",
    "IsLoyal",
    "IsPushover",
    "IsQuitter",
    "IsShy"
  ],
  "bAND"     : false
},
{
  "strName" : "TIsSeekAutonomyAllowUs",
  "fChance" : 0.75,
  "fCount"  : 0.0,
  "aReqs"   : [
    "IsAmbitious",
    "IsArrogant",
    "IsDiligent",
    "IsFinicky",
    "IsPatient",
    "IsStubborn"
  ],
  "aForbids" : [
    "IsApathetic",
    "IsComplacent",
    "IsCraven",
    "IsFollower",
    "IsHumble",
    "IsImpatient",
    "IsPushover",
    "IsQuitter"
  ],
  "bAND"     : false
},
{
  "strName" : "TIsSeekAutonomyDenyUs",
  "fChance" : 0.75,
  "fCount"  : 0.0,
  "aReqs"   : [
    "IsStrong",
    "IsTough",
    "SkillMeleeArmed",
    "SkillMeleeUnarmed"
  ],
  "aForbids" : [
    "IsApathetic",
    "IsCraven",
    "IsKind",
    "IsPushover",
    "IsShy",
    "IsFeeble",
    "IsFragile"
  ],
  "bAND"     : false
},
{
  "strName" : "TIsSeekContactUs",
  "fChance" : 1.0,
  "fCount"  : 0.0,
  "aReqs"   : [
    "SkillPersuade",
    "SkillSciencePsychology",
    "IsCharismatic",
    "IsComedian",
    "IsGregarious",
    "IsLeader",
    "IsObservant"
  ],
  "aForbids" : [
    "IsShy"
  ],
  "aTriggersForbid" :[
	"TNoDiscomfortsSocial"
  ],
  "bAND"     : false
},
{
  "strName" : "TIsSeekContactAllowUs",
  "fChance" : 0.75,
  "fCount"  : 0.0,
  "aForbids" : [
    "IsImpatient"
  ],
  "aTriggersForbid" :[
	"TNoDiscomfortsSocial"
  ],
  "bAND"     : false
},
{
  "strName" : "TIsSeekContactDenyUs",
  "fChance" : 0.75,
  "fCount"  : 0.0,
  "aReqs"   : [
    "IsArrogant",
    "IsCruel",
    "IsOblivious",
    "IsSelfish"
  ],
  "aForbids" : [
    "IsGregarious",
    "IsHumble",
    "IsKind",
    "IsSelfless"
  ],
  "bAND"     : false
},
{
  "strName" : "TIsSeekContactNotMuchUs",
  "fChance" : 0.75,
  "fCount"  : 0.0,
  "aReqs"   : [
  ],
  "aForbids" : [
  ],
  "aTriggersForbid" :[
	"TNoDiscomfortsSocial"
  ],
  "bAND"     : false
},
{
  "strName" : "TIsSeekContactN3Us",
  "fChance" : 1.0,
  "fCount"  : 0.0,
  "aReqs"   : [
    "IsFanViceroys"
  ],
  "aForbids" : [
  ],
  "aTriggersForbid" :[
	"TNoDiscomfortsSocial"
  ],
  "bAND"    : false
},
{
  "strName" : "TIsSeekContactN3AgitatedSmokeUs",
  "fChance" : 0.75,
  "fCount"  : 0.0,
  "aReqs"   : [
    "IsArrogant",
    "IsCruel",
    "IsFinicky",
    "IsImpatient",
    "IsPatient",
    "IsPessimist",
    "IsSelfish",
    "IsTreacherous",
    "IsVengeful"
  ],
  "aForbids" : [
    "IsFollower",
    "IsForgiving",
    "IsKind",
    "IsOptimist",
    "IsPushover",
    "IsQuitter",
    "IsSelfless",
    "IsShy",
    "IsTidy"
  ],
  "bAND"     : false
},
{
  "strName" : "TIsSeekContactN3AllowUs",
  "fChance" : 1.0,
  "fCount"  : 0.0,
  "aReqs"   : [
    "IsFanViceroys",
    "IsFollower",
    "IsGlutton",
    "IsGregarious",
    "IsPushover"
  ],
  "bAND"    : false
},
{
  "strName" : "TIsSeekContactN3BitterSmokeUs",
  "fChance" : 0.75,
  "fCount"  : 0.0,
  "aReqs"   : [
    "IsApathetic",
    "IsArrogant",
    "IsHumorless",
    "IsOblivious",
    "IsRepulsive",
    "IsShy"
  ],
  "aForbids" : [
    "IsCharismatic",
    "IsComedian",
    "IsFinicky",
    "IsGregarious",
    "IsLeader"
  ],
  "bAND"     : false
},
{
  "strName" : "TIsSeekContactN3DenyUs",
  "fChance" : 1.0,
  "fCount"  : 0.0,
  "aReqs"   : [
    "IsFinicky",
    "IsImpatient",
    "IsOblivious"
  ],
  "aForbids" : [
    "IsGlutton",
    "IsGregarious",
    "IsPushover"
  ],
  "bAND"     : false
},
{
  "strName" : "TIsSeekContactN3HappySmokeUs",
  "fChance" : 0.75,
  "fCount"  : 0.0,
  "aReqs"   : [
    "IsApathetic",
    "IsFollower",
    "IsHumble",
    "IsOblivious",
    "IsObservant",
    "IsObtuse",
    "IsPatient",
    "IsPushover",
    "IsShy"
  ],
  "aForbids" : [
    "IsComedian",
    "IsGregarious",
    "IsImpatient",
    "IsQuitter",
    "IsRepulsive"
  ],
  "aTriggersForbid" :[
	"TNoDiscomfortsSocial"
  ],
  "bAND"     : false
},
{
  "strName" : "TIsSeekContactN3WrongBrandUs",
  "fChance" : 1.0,
  "fCount"  : 0.0,
  "aReqs"   : [
    "IsArrogant",
    "IsFinicky",
    "IsLoyal",
    "IsPessimist",
    "IsSelfish",
    "IsStubborn"
  ],
  "aForbids" : [
    "IsApathetic",
    "IsFollower",
    "IsGlutton",
    "IsGregarious",
    "IsOptimist",
    "IsPushover",
    "IsSelfless",
    "IsTreacherous"
  ],
  "bAND"     : false
},
{
  "strName" : "TIsSeekEsteemUs",
  "fChance" : 0.125,
  "fCount"  : 0.0,
  "aReqs"   : [
    "IsComedian",
    "IsGenius",
    "IsGregarious",
    "IsMasochist",
    "IsObservant",
    "IsObtuse"
  ],
  "aForbids" : [
    "IsCruel",
    "IsHumorless",
    "IsOblivious"
  ],
  "aTriggersForbid" :[
	"TNoDiscomfortsSocial"
  ],
  "bAND"     : false
},
{
  "strName" : "TIsSeekEsteemAllowUs",
  "fChance" : 0.6,
  "fCount"  : 0.0,
  "aReqs"   : [
    "IsComedian",
    "IsForgiving",
    "IsGregarious",
    "IsKind",
    "IsLeader",
    "IsObtuse",
    "IsOptimist"
  ],
  "aForbids" : [
    "IsApathetic",
    "IsArrogant",
    "IsCruel",
    "IsFinicky",
    "IsHumorless",
    "IsPessimist",
    "IsShy"
  ],
  "aTriggersForbid" :[
	"TNoDiscomfortsSocial"
  ],
  "bAND"     : false
},
{
  "strName" : "TIsSeekEsteemDenyUs",
  "fChance" : 0.75,
  "fCount"  : 0.0,
  "aReqs"   : [
    "IsArrogant",
    "IsCruel",
    "IsHumorless",
    "IsSelfish"
  ],
  "aForbids" : [
    "IsGregarious",
    "IsFollower",
    "IsHumble",
    "IsKind",
    "IsPushover",
    "IsSelfless",
    "IsShy"
  ],
  "bAND"     : false
},
{
  "strName" : "TIsSeekEsteemN2Us",
  "fChance" : 0.5,
  "fCount"  : 0.0,
  "aReqs"   : [
    "IsAmbitious",
    "IsArrogant",
    "IsDiligent",
    "IsGenius",
    "IsHumorless",
    "IsOblivious"
  ],
  "aForbids" : [
    "IsCharismatic",
    "IsComplacent",
    "IsHumble",
    "IsObtuse",
    "IsQuitter"
  ],
  "aTriggersForbid" :[
	"TNoDiscomfortsSocial"
  ],
  "bAND"     : false
},
{
  "strName" : "TIsSeekEsteemN2AllowUs",
  "fChance" : 0.8,
  "fCount"  : 0.0,
  "aReqs"   : [
    "IsDiligent",
    "IsFollower",
    "IsGregarious",
    "IsHumble",
    "IsKind",
    "IsLeader",
    "IsObservant",
    "IsPatient",
    "IsPushover",
    "IsSelfless"
  ],
  "aForbids" : [
    "IsApathetic",
    "IsImpatient",
    "IsOblivious",
    "IsObtuse",
    "IsSelfish"
  ],
  "bAND"     : false
},
{
  "strName" : "TIsSeekEsteemN2DenyUs",
  "fChance" : 0.7,
  "fCount"  : 0.0,
  "aReqs"   : [
    "IsApathetic",
    "IsImpatient",
    "IsOblivious",
    "IsObtuse",
    "IsSelfish"
  ],
  "aForbids" : [
    "IsDiligent",
    "IsFollower",
    "IsGregarious",
    "IsHumble",
    "IsKind",
    "IsLeader",
    "IsObservant",
    "IsPatient",
    "IsPushover",
    "IsSelfless"
  ],
  "bAND"     : false
},
{
  "strName" : "TIsSeekEsteemN2DenyAuthoritativeUs",
  "fChance" : 0.75,
  "fCount"  : 0.0,
  "aReqs"   : [
    "IsArrogant",
    "IsCruel",
    "IsHumorless",
    "IsImpatient",
    "IsLeader",
    "IsObtuse",
    "IsRepulsive"
  ],
  "aForbids" : [
    "IsApathetic",
    "IsCharismatic",
    "IsDiligent",
    "IsFollower",
    "IsForgiving",
    "IsHumble",
    "IsKind",
    "IsPatient",
    "IsPushover",
    "IsShy"
  ],
  "bAND"     : false
},
{
  "strName" : "TIsSeekEsteemN2ReplyInKindUs",
  "fChance" : 0.33,
  "fCount"  : 0.0,
  "aReqs"   : [
    "IsAmbitious",
    "IsArrogant",
    "IsCruel",
    "IsFinicky",
    "IsGenius",
    "IsOblivious",
    "IsRepulsive",
    "IsVengeful"
  ],
  "aForbids" : [
    "IsApathetic",
    "IsCharismatic",
    "IsComplacent",
    "IsFollower",
    "IsForgiving",
    "IsHumble",
    "IsObtuse",
    "IsPushover",
    "IsQuitter",
    "IsShy"
  ],
  "bAND"     : false
},
{
  "strName" : "TIsSeekFriendshipUs",
  "fChance" : 0.75,
  "fCount"  : 0.0,
  "aForbids" : [
  ],
  "aTriggersForbid" :[
	"TNoDiscomfortsSocial"
  ],
  "bAND"    : false
},
{
  "strName" : "TIsSeekFriendshipAllowUs",
  "fChance" : 1.0,
  "fCount"  : 0.0,
  "aForbids" : [
  ],
  "aTriggersForbid" :[
	"TNoDiscomfortsSocial"
  ],
  "bAND"    : false
},
{
  "strName" : "TIsSeekFriendshipDenyUs",
  "fChance" : 0.75,
  "fCount"  : 0.0,
  "aReqs"   : [
    "IsArrogant",
    "IsCruel",
    "IsOblivious",
    "IsSelfish"
  ],
  "aForbids" : [
    "IsGregarious",
    "IsHumble",
    "IsKind",
    "IsSelfless"
  ],
  "bAND"     : false
},
{
  "strName" : "TIsSeekFriendshipN2Us",
  "fChance" : 0.8,
  "fCount"  : 0.0,
  "aReqs"   : [
    "IsFanBreakoutShooters",
    "IsFanBreakoutWarriors",
    "IsCharismatic",
    "IsGregarious",
    "IsLeader"
  ],
  "aForbids" : [
    "IsShy"
  ],
  "aTriggersForbid" :[
	"TNoDiscomfortsSocial"
  ],
  "bAND"     : false
},
{
  "strName" : "TIsSeekFriendshipN2AllowGeneralUs",
  "fChance" : 0.75,
  "fCount"  : 0.0,
  "aReqs"   : [
    "IsFanBreakoutShooters",
    "IsFanBreakoutWarriors"
  ],
  "aForbids" : [
  ],
  "aTriggersForbid" :[
	"TNoDiscomfortsSocial"
  ],
  "bAND"    : false
},
{
  "strName" : "TIsSeekFriendshipN2AllowShootersUs",
  "fChance" : 0.75,
  "fCount"  : 0.0,
  "aReqs"   : [
    "IsFanBreakoutShooters"
  ],
  "aForbids" : [
  ],
  "aTriggersForbid" :[
	"TNoDiscomfortsSocial"
  ],
  "bAND"    : false
},
{
  "strName" : "TIsSeekFriendshipN2AllowWarriorsUs",
  "fChance" : 0.75,
  "fCount"  : 0.0,
  "aReqs"   : [
    "IsFanBreakoutWarriors"
  ],
  "aForbids" : [
  ],
  "aTriggersForbid" :[
	"TNoDiscomfortsSocial"
  ],
  "bAND"    : false
},
{
  "strName" : "TIsSeekFriendshipN2CatchUs",
  "fChance" : 0.75,
  "fCount"  : 0.0,
  "aReqs"   : [
    "IsFanBreakoutShooters",
    "IsFanBreakoutWarriors"
  ],
  "aForbids" : [
  ],
  "aTriggersForbid" :[
	"TNoDiscomfortsSocial"
  ],
  "bAND"    : false
},
{
  "strName" : "TIsSeekFriendshipN2DenyUs",
  "fChance" : 1.0,
  "fCount"  : 0.0,
  "bAND"    : false
},
{
  "strName" : "TIsSeekFriendshipN2FumbleUs",
  "fChance" : 0.75,
  "fCount"  : 0.0,
  "aReqs"   : [
    "IsFanBreakoutShooters",
    "IsFanBreakoutWarriors"
  ],
  "aForbids" : [
  ],
  "aTriggersForbid" :[
	"TNoDiscomfortsSocial"
  ],
  "bAND"    : false
},
{
  "strName" : "TIsSeekIntimacyUs",
  "fChance" : 0.75,
  "fCount"  : 0.0,
  "aReqs"   : [
    "IsAmbitious",
    "IsArrogant",
    "IsBrave",
    "IsCharismatic",
    "IsGregarious",
    "IsLeader",
    "IsLustful",
    "IsOptimist",
    "IsRepulsive"
  ],
  "aForbids" : [
    "IsApathetic",
    "IsChaste",
    "IsComplacent",
    "IsCraven",
    "IsPessimist",
    "IsShy"
  ],
  "aTriggersForbid" :[
	"TNoDiscomfortsSocial"
  ],
  "bAND"     : false
},
{
  "strName" : "TIsSeekIntimacyAllowUs",
  "fChance" : 0.75,
  "fCount"  : 0.0,
  "aForbids" : [
    "IsChaste",
    "IsCraven",
    "IsFollower",
    "IsPessimist",
    "IsQuitter",
    "IsShy"
  ],
  "aTriggersForbid" :[
	"TNoDiscomfortsSocial"
  ],
  "bAND"     : false
},
{
  "strName" : "TIsSeekIntimacyDenyUs",
  "fChance" : 0.75,
  "fCount"  : 0.0,
  "aReqs"   : [
    "IsArrogant",
    "IsChaste",
    "IsCruel",
    "IsFinicky",
    "IsOblivious",
    "IsRepulsive",
    "IsTreacherous",
    "IsVengeful"
  ],
  "aForbids" : [
    "IsCharismatic",
    "IsForgiving",
    "IsHumble",
    "IsKind",
    "IsLustful",
    "IsShy"
  ],
  "aTriggersForbid" :[
	"TNoDiscomfortsSocial"
  ],
  "bAND"     : false
},
{
  "strName" : "TIsSeekIntimacyN2Us",
  "fChance" : 0.5,
  "fCount"  : 0.0,
  "aForbids" : [
    "IsTemperate"
  ],
  "bAND"     : false
},
{
  "strName" : "TIsSeekIntimacyN2AllowUs",
  "fChance" : 0.75,
  "fCount"  : 0.0,
  "aReqs"   : [
    "IsApathetic",
    "IsComplacent",
    "IsFollower",
    "IsGlutton",
    "IsGregarious",
    "IsKind",
    "IsLustful",
    "IsPushover",
    "IsTrusting"
  ],
  "aForbids" : [
    "IsTemperate"
  ],
  "aTriggersForbid" :[
	"TNoDiscomfortsSocial"
  ],
  "bAND"     : false
},
{
  "strName" : "TIsSeekIntimacyN2AllowEnthusiasticUs",
  "fChance" : 0.75,
  "fCount"  : 0.0,
  "aForbids" : [
    "IsChaste",
    "IsCraven",
    "IsFollower",
    "IsPessimist",
    "IsQuitter",
    "IsShy",
    "IsTemperate"
  ],
  "aTriggersForbid" :[
	"TNoDiscomfortsSocial"
  ],
  "bAND"     : false
},
{
  "strName" : "TIsSeekIntimacyN2DenyUs",
  "fChance" : 1.0,
  "fCount"  : 0.0,
  "bAND"    : false
},
{
  "strName" : "TIsSeekKillDenyUs",
  "fChance" : 1.0,
  "fCount"  : 0.0,
  "aForbids" : [
    "IsCoordinated",
    "IsStrong",
    "IsTough",
    "SkillMeleeArmed",
    "SkillMeleeUnarmed"
  ],
  "bAND"     : false
},
{
  "strName" : "TIsSeekKillTargetUs",
  "fChance" : 0.05,
  "fCount"  : 0.0,
  "aReqs"   : [
    "IsTreacherous",
    "IsVengeful",
    "DcAutonomy05",
    "DcEsteem05",
    "DcSecurity05",
    "DcWeird03",
    "DcWeird04"
  ],
  "aForbids" : [
    "IsForgiving",
    "IsKind"
  ],
  "bAND"     : false
},
{
  "strName" : "TIsSeekKODenyUs",
  "fChance" : 1.0,
  "fCount"  : 0.0,
  "aForbids" : [
    "IsCoordinated",
    "IsStrong",
    "IsTough",
    "SkillMeleeArmed",
    "SkillMeleeUnarmed"
  ],
  "bAND"     : false
},
{
  "strName" : "TIsSeekKOTargetUs",
  "fChance" : 0.05,
  "fCount"  : 0.0,
  "aReqs"   : [
    "IsTreacherous",
    "IsVengeful",
    "DcAutonomy05",
    "DcEsteem05",
    "DcSecurity05",
    "DcWeird03",
    "DcWeird04"
  ],
  "aForbids" : [
    "IsForgiving",
    "IsKind"
  ],
  "bAND"     : false
},
{
  "strName" : "TIsSeekMeaningUs",
  "fChance" : 0.75,
  "fCount"  : 0.0,
  "aReqs"   : [
    "IsApathetic",
    "IsHonest",
    "IsOblivious",
    "IsPessimist",
    "IsQuitter",
    "IsSelfish"
  ],
  "aForbids" : [
    "IsLiar",
    "IsOptimist",
    "IsSelfless"
  ],
  "aTriggersForbid" :[
	"TNoDiscomfortsSocial"
  ],
  "bAND"     : false
},
{
  "strName" : "TIsSeekMeaningAllowUs",
  "fChance" : 1.0,
  "fCount"  : 0.0,
  "aReqs"   : [
    "IsCharismatic",
    "IsKind",
    "IsLeader",
    "IsObservant",
    "IsOptimist",
    "IsPatient"
  ],
  "aForbids" : [
    "IsApathetic",
    "IsArrogant",
    "IsCruel",
    "IsImpatient",
    "IsOblivious",
    "IsPessimist",
    "IsQuitter"
  ],
  "aTriggersForbid" :[
	"TNoDiscomfortsSocial"
  ],
  "bAND"     : false
},
{
  "strName" : "TIsSeekMeaningDenyUs",
  "fChance" : 0.75,
  "fCount"  : 0.0,
  "aReqs"   : [
    "IsArrogant",
    "IsCruel",
    "IsHumorless",
    "IsImpatient",
    "IsPessimist",
    "IsQuitter"
  ],
  "aForbids" : [
    "IsCharismatic",
    "IsGregarious",
    "IsHumble",
    "IsKind",
    "IsOptimist",
    "IsShy"
  ],
  "bAND"     : false
},
{
  "strName" : "TIsSeekMeaningN3Us",
  "fChance" : 0.75,
  "fCount"  : 0.0,
  "aForbids" : [
  ],
  "aTriggersForbid" :[
	"TNoDiscomfortsSocial"
  ],
  "bAND"    : false
},
{
  "strName" : "TIsSeekMeaningN3AllowUs",
  "fChance" : 0.75,
  "fCount"  : 0.0,
  "aForbids" : [
    "IsApathetic",
    "IsHumorless"
  ],
  "bAND"     : false
},
{
  "strName" : "TIsSeekMeaningN3DenyUs",
  "fChance" : 0.8,
  "fCount"  : 0.0,
  "aReqs"   : [
    "IsAgliophobic",
    "IsCraven",
    "IsHumorless",
    "IsKind",
    "IsPessimist"
  ],
  "aForbids" : [
    "IsApathetic",
    "IsBrave",
    "IsComedian",
    "IsCruel",
    "IsFollower",
    "IsOblivious",
    "IsOptimist",
    "IsTreacherous"
  ],
  "bAND"     : false
},
{
  "strName" : "TIsSeekSecurityUs",
  "fChance" : 0.5,
  "fCount"  : 0.0,
  "aReqs"   : [
    "IsCraven",
    "IsFollower",
    "IsGregarious",
    "IsHumble",
    "IsKind",
    "IsLustful",
    "IsOblivious",
    "IsOptimist",
    "IsSelfish",
    "IsTrusting"
  ],
  "aForbids" : [
    "IsApathetic",
    "IsArrogant",
    "IsBrave",
    "IsCruel",
    "IsLeader",
    "IsMasochist",
    "IsPessimist",
    "IsSelfless",
    "IsShy",
    "IsStubborn",
    "IsTreacherous"
  ],
  "aTriggersForbid" :[
	"TNoDiscomfortsSocial"
  ],
  "bAND"     : false
},
{
  "strName" : "TIsSeekSecurityAllowUs",
  "fChance" : 0.75,
  "fCount"  : 0.0,
  "aReqs"   : [
    "IsBrave",
    "IsCharismatic",
    "IsCraven",
    "IsFollower",
    "IsForgiving",
    "IsGregarious",
    "IsHumble",
    "IsKind",
    "IsLustful",
    "IsPatient",
    "IsPushover",
    "IsSelfless",
    "IsTrusting"
  ],
  "aForbids" : [
    "IsApathetic",
    "IsArrogant",
    "IsChaste",
    "IsCruel",
    "IsImpatient",
    "IsRepulsive",
    "IsSelfish",
    "IsShy",
    "IsTreacherous",
    "IsVengeful"
  ],
  "aTriggersForbid" :[
	"TNoDiscomfortsSocial"
  ],
  "bAND"     : false
},
{
  "strName" : "TIsSeekSecurityDenyUs",
  "fChance" : 0.2,
  "fCount"  : 0.0,
  "aReqs"   : [
    "IsArrogant",
    "IsCruel",
    "IsRepulsive",
    "IsTreacherous",
    "IsVengeful"
  ],
  "aForbids" : [
    "IsAgliophobic",
    "IsApathetic",
    "IsCharismatic",
    "IsCraven",
    "IsFollower",
    "IsForgiving",
    "IsGregarious",
    "IsHumble",
    "IsKind",
    "IsPatient",
    "IsPushover",
    "IsShy"
  ],
  "bAND"     : false
},
{
  "strName" : "TIsSeekSecurityN2Us",
  "fChance" : 0.5,
  "fCount"  : 0.0,
  "aReqs"   : [
    "IsAgliophobic",
    "IsAmbitious",
    "IsArrogant",
    "IsCraven",
    "IsDiligent",
    "IsFinicky",
    "IsFollower",
    "IsLoyal",
    "IsObservant",
    "IsObtuse",
    "IsPessimist"
  ],
  "aForbids" : [
    "IsApathetic",
    "IsComplacent",
    "IsHumble",
    "IsOblivious",
    "IsOptimist"
  ],
  "aTriggersForbid" :[
	"TNoDiscomfortsSocial"
  ],
  "bAND"     : false
},
{
  "strName" : "TIsSeekSecurityN2AllowUs",
  "fChance" : 0.7,
  "fCount"  : 0.0,
  "aReqs"   : [
    "IsAgliophobic",
    "IsAmbitious",
    "IsCraven",
    "IsDiligent",
    "IsFinicky",
    "IsFollower",
    "IsLoyal",
    "IsOblivious",
    "IsObservant",
    "IsObtuse",
    "IsPessimist",
    "IsPushover",
    "IsTrusting",
    "IsApathetic"
  ],
  "aForbids" : [
    "IsComplacent",
    "IsGenius",
    "IsMasochist",
    "IsOptimist"
  ],
  "bAND"     : false
},
{
  "strName" : "TIsSeekSecurityN2DenyUs",
  "fChance" : 0.75,
  "fCount"  : 0.0,
  "aReqs"   : [
    "IsApathetic",
    "IsArrogant",
    "IsBrave",
    "IsComplacent",
    "IsCruel",
    "IsGenius",
    "IsLoyal",
    "IsOptimist",
    "IsRepulsive",
    "IsStubborn",
    "IsTreacherous"
  ],
  "aForbids" : [
    "IsAgliophobic",
    "IsCraven",
    "IsDiligent",
    "IsFollower",
    "IsHumble",
    "IsKind",
    "IsMasochist",
    "IsObtuse",
    "IsPessimist",
    "IsPushover",
    "IsShy",
    "IsTrusting"
  ],
  "bAND"     : false
},
{
  "strName" : "TIsSeekSecurityN3Us",
  "fChance" : 1.0,
  "fCount"  : 0.0,
  "aForbids" : [
    "DcAutonomy05",
    "DcEsteem05",
    "DcSecurity05",
    "DcSelfRespect05"
  ],
  "bAND"    : false
},
{
  "strName" : "TIsSeekSecurityN3AllowUs",
  "fChance" : 0.8,
  "fCount"  : 0.0,
  "bAND"    : false
},
{
  "strName" : "TIsSeekSelfRespectUs",
  "fChance" : 1.0,
  "fCount"  : 0.0,
  "aForbids" : [
    "IsApathetic",
    "IsHumble",
    "IsTemperate"
  ],
  "aTriggersForbid" :[
  ],
  "bAND"     : false
},
{
  "strName" : "TIsSeekSelfRespectDenyUs",
  "fChance" : 0.75,
  "fCount"  : 0.0,
  "aReqs"   : [
    "IsAmbitious",
    "IsArrogant",
    "IsComedian",
    "IsCruel",
    "IsRepulsive",
    "IsTreacherous",
    "IsVengeful"
  ],
  "aForbids" : [
    "IsApathetic",
    "IsCharismatic",
    "IsComplacent",
    "IsForgiving",
    "IsHumble",
    "IsKind",
    "IsShy"
  ],
  "bAND"     : false
},
{
  "strName" : "TIsSeekSelfRespectN2Us",
  "fChance" : 0.3,
  "fCount"  : 0.0,
  "aReqs"   : [
    "IsAgliophobic",
    "IsCraven",
    "IsFinicky",
    "IsHonest",
    "IsObservant",
    "IsPessimist",
    "IsQuitter",
    "IsSelfish",
    "IsTrusting"
  ],
  "aForbids" : [
    "IsApathetic",
    "IsArrogant",
    "IsBrave",
    "IsCruel",
    "IsLiar",
    "IsOblivious",
    "IsOptimist",
    "IsSelfless",
    "IsShy",
    "IsTreacherous"
  ],
  "aTriggersForbid" :[
	"TNoDiscomfortsSocial"
  ],
  "bAND"    : false
},
{
  "strName" : "TIsSeekSelfRespectN2AllowUs",
  "fChance" : 0.6,
  "fCount"  : 0.0,
  "aReqs"   : [
    "IsCharismatic",
    "IsGenius",
    "IsGregarious",
    "IsHumble",
    "IsKind",
    "IsObservant",
    "IsOptimist",
    "IsPatient",
    "IsSelfless"
  ],
  "aForbids" : [
    "IsArrogant",
    "IsCruel",
    "IsImpatient",
    "IsOblivious",
    "IsPessimist",
    "IsQuitter",
    "IsRepulsive",
    "IsSelfish",
    "IsTreacherous"
  ],
  "aTriggersForbid" :[
	"TNoDiscomfortsSocial"
  ],
  "bAND"    : false
},
{
  "strName" : "TIsSeekSelfRespectN2DenyUs",
  "fChance" : 0.75,
  "fCount"  : 0.0,
  "aReqs"   : [
    "IsArrogant",
    "IsCruel",
    "IsImpatient",
    "IsOblivious",
    "IsRepulsive",
    "IsSelfish",
    "IsTreacherous",
    "IsVengeful"
  ],
  "aForbids" : [
    "IsCharismatic",
    "IsFollower",
    "IsForgiving",
    "IsGregarious",
    "IsHumble",
    "IsKind",
    "IsPatient",
    "IsPushover",
    "IsSelfless",
    "IsShy"
  ],
  "bAND"     : false
},
{
  "strName" : "TIsSeekSocialDeny",
  "fChance" : 0.5,
  "fCount"  : 0.0,
  "aReqs"   : [
  ],
  "aForbids" : [
    "IsPlayer"
  ],
  "aTriggers" :[
    "TDiscomfortsSocial"
  ],
  "bAND"     : false
},
{
  "strName" : "TIsSOCAccuseAffairUs",
  "fChance" : 1.0,
  "fCount"  : 0.0,
  "aReqs"   : [
    "IsHarrassExsNewDone"
  ],
  "aForbids" : [
  ],
  "bAND"     : false
},
{
  "strName" : "TIsSOCBackAwaySlowUs",
  "fChance" : 0.75,
  "fCount"  : 0.0,
  "bAND"    : false
},
{
  "strName" : "TIsSOCCalmDownThem",
  "fChance" : 1.0,
  "fCount"  : 0.0,
  "aReqs" : [
    "DcSecurity05",
    "IsHuman"
  ],
  "aForbids" : [
    "Unconscious"
  ],
  "bAND"    : true
},
{
  "strName" : "TIsSOCCalmDownUs",
  "fChance" : 1.0,
  "fCount"  : 0.0,
  "aForbids" : [
    "DcSecurity05"
  ],
  "bAND"    : true
},
{
  "strName" : "TIsSOCChangeSubjectUs",
  "fChance" : 0.7,
  "fCount"  : 0.0,
  "bAND"    : false
},
{
  "strName" : "TIsSOCCraftDarkJokeUs",
  "fChance" : 0.4,
  "fCount"  : 0.0,
  "aReqs"   : [
    "IsComedian"
  ],
  "aForbids" : [
    "IsHumorless"
  ],
  "bAND"     : false
},
{
  "strName" : "TIsSOCEmergStepAsideUs",
  "fChance" : 0.8,
  "fCount"  : 0.0,
  "aReqs"   : [
    "IsAgliophobic",
    "IsApathetic",
    "IsComplacent",
    "IsCraven",
    "IsFollower",
    "IsHumble",
    "IsObservant",
    "IsPushover",
    "IsQuitter",
    "IsShy",
    "IsTrusting"
  ],
  "aForbids" : [
    "IsAmbitious",
    "IsArrogant",
    "IsLeader",
    "IsOblivious",
    "IsStubborn"
  ],
  "bAND"     : false
},
{
  "strName" : "TIsSOCEncourageUs",
  "fChance" : 1.0,
  "fCount"  : 0.0,
  "aReqs"   : [
    "IsCharismatic",
    "IsGregarious",
    "IsKind",
    "IsLeader",
    "IsObservant",
    "IsOptimist",
    "IsPatient"
  ],
  "aForbids" : [
    "IsApathetic",
    "IsCruel",
    "IsOblivious",
    "IsPessimist",
    "IsRepulsive",
    "IsTreacherous"
  ],
  "aTriggersForbid" :[
	"TNoDiscomfortsSocial"
  ],
  "bAND"     : false
},
{
  "strName" : "TIsSOCHarassExsNew01Us",
  "fChance" : 1.0,
  "fCount"  : 0.0,
  "aReqs"   : [
  ],
  "aForbids" : [
    "IsHarrassExsNewDone"
  ],
  "bAND"     : false
},
{
  "strName" : "TIsSOCHireAllow",
  "fChance" : 1.0,
  "fCount"  : 0.0,
  "aReqs"   : [
  ],
  "aForbids" : [
  ],
  "aTriggersForbid" :[
	"TNoDiscomfortsSocial"
  ],
  "bAND"     : false
},
{
  "strName" : "TIsSOCLaughCallousUs",
  "fChance" : 0.3,
  "fCount"  : 0.0,
  "aReqs"   : [
    "IsAmbitious",
    "IsArrogant",
    "IsComedian",
    "IsCruel",
    "IsRepulsive",
    "IsTreacherous",
    "IsVengeful"
  ],
  "aForbids" : [
    "IsApathetic",
    "IsCharismatic",
    "IsComplacent",
    "IsForgiving",
    "IsHumble",
    "IsKind",
    "IsShy"
  ],
  "bAND"     : false
},
{
  "strName" : "TIsSOCPlayfulThreatUs",
  "fChance" : 0.3,
  "fCount"  : 0.0,
  "aReqs"   : [
    "IsCharismatic",
    "IsComedian",
    "IsGregarious",
    "IsLeader",
    "IsLustful",
    "IsVengeful"
  ],
  "aForbids" : [
    "IsFollower",
    "IsHumorless",
    "IsOblivious",
    "IsRepulsive",
    "IsShy",
    "IsTreacherous"
  ],
  "aTriggersForbid" :[
	"TNoDiscomfortsSocial"
  ],
  "bAND"     : false
},
{
  "strName" : "TIsSOCPleeeaseUs",
  "fChance" : 0.5,
  "fCount"  : 0.0,
  "aReqs"   : [
    "IsAmbitious",
    "IsGlutton",
    "IsObtuse",
    "IsOptimist",
    "IsRepulsive",
    "IsSelfish",
    "IsStubborn"
  ],
  "aForbids" : [
    "IsApathetic",
    "IsArrogant",
    "IsCharismatic",
    "IsComplacent",
    "IsFollower",
    "IsLeader",
    "IsPessimist",
    "IsPushover",
    "IsQuitter",
    "IsSelfless",
    "IsShy",
    "IsTemperate",
    "IsTreacherous"
  ],
  "aTriggersForbid" :[
	"TNoDiscomfortsSocial"
  ],
  "bAND"     : false
},
{
  "strName" : "TIsSOCPoliteChuckleUs",
  "fChance" : 0.2,
  "fCount"  : 0.0,
  "aReqs"   : [
  ],
  "aForbids" : [
  ],
  "aTriggersForbid" :[
	"TNoDiscomfortsSocial"
  ],
  "bAND"     : false
},
{
  "strName" : "TIsSOCQuiver",
  "fChance" : 1.0,
  "fCount"  : 0.0,
  "aReqs"   : [
    "DcSecurity05"
  ],
  "aForbids" : [
  ],
  "aTriggersForbid" :[
  ],
  "bAND"     : false
},
{
  "strName" : "TIsSOCSmileDemurelyUs",
  "fChance" : 0.2,
  "fCount"  : 0.0,
  "aReqs"   : [
  ],
  "aForbids" : [
  ],
  "aTriggersForbid" :[
	"TNoDiscomfortsSocial"
  ],
  "bAND"     : false
},
{
  "strName" : "TIsSOCReassureLogicalUs",
  "fChance" : 0.8,
  "fCount"  : 0.0,
  "aReqs"   : [
    "IsGenius",
    "IsObservant"
  ],
  "aForbids" : [
    "IsCruel",
    "IsOblivious",
    "IsObtuse",
    "IsTreacherous"
  ],
  "aTriggersForbid" :[
	"TNoDiscomfortsSocial"
  ],
  "bAND"     : false
},
{
  "strName" : "TIsSOCReiterateUrgencyUs",
  "fChance" : 0.4,
  "fCount"  : 0.0,
  "aReqs"   : [
    "DcSecurity04",
    "DcSecurity05",
    "IsAmbitious",
    "IsCraven",
    "IsDiligent",
    "IsImpatient",
    "IsLeader",
    "IsPessimist"
  ],
  "aForbids" : [
    "IsApathetic",
    "IsComplacent",
    "IsOblivious"
  ],
  "aTriggersForbid" :[
  ],
  "bAND"     : false
},
{
  "strName" : "TIsSOCRepeatSexuallyUs",
  "fChance" : 0.8,
  "fCount"  : 0.0,
  "aReqs"   : [
    "IsAmbitious",
    "IsArrogant",
    "IsBrave",
    "IsComedian",
    "IsGregarious",
    "IsLeader",
    "IsLustful",
    "IsOptimist",
    "IsRepulsive"
  ],
  "aForbids" : [
    "IsAgliophobic",
    "IsApathetic",
    "IsCharismatic",
    "IsChaste",
    "IsComplacent",
    "IsCraven",
    "IsFollower",
    "IsHumorless",
    "IsPessimist",
    "IsQuitter",
    "IsShy"
  ],
  "aTriggersForbid" :[
	"TNoDiscomfortsSocial"
  ],
  "bAND"     : false
},
{
  "strName" : "TIsSOCThreatStepAsideUs",
  "fChance" : 0.4,
  "fCount"  : 0.0,
  "aReqs"   : [
    "IsAgliophobic",
    "IsApathetic",
    "IsComplacent",
    "IsCraven",
    "IsFollower",
    "IsHumble",
    "IsPushover",
    "IsQuitter",
    "IsShy",
    "IsTrusting"
  ],
  "aForbids" : [
    "IsAmbitious",
    "IsArrogant",
    "IsBrave",
    "IsLeader",
    "IsMasochist",
    "IsStubborn",
    "IsVengeful"
  ],
  "bAND"     : false
},
{
  "strName" : "TIsSOCYawnInFaceUs",
  "fChance" : 0.75,
  "fCount"  : 0.0,
  "aReqs"   : [
    "IsApathetic",
    "IsArrogant",
    "IsCruel",
    "IsFinicky",
    "IsGregarious",
    "IsHumble",
    "IsKind",
    "IsPatient",
    "IsShy"
  ],
  "aForbids" : [
    "IsCharismatic",
    "IsFollower",
    "IsImpatient",
    "IsRepulsive",
    "IsTreacherous"
  ],
  "bAND"     : false
},
{
  "strName" : "TIsSOCYesSirUs",
  "fChance" : 0.5,
  "fCount"  : 0.0,
  "aForbids" : [
    "IsLeader",
    "IsTreacherous"
  ],
  "aTriggersForbid" :[
	"TNoDiscomfortsSocial"
  ],
  "bAND"     : false
}
] 