[
  {
    "strName" : "CGEncContactAdult",
    "strInteraction" : "CGEncContactAdult",
    "fShipCashReward" : 0.0,
    "fStartATCRange" : 0.0,
    "strStartATC" : "",
    "strShipRewards" : ""
  },
  {
    "strName" : "CGEncContactCriminal",
    "strInteraction" : "CGEncContactCriminal",
    "fShipCashReward" : 0.0,
    "fStartATCRange" : 0.0,
    "strStartATC" : "",
    "strShipRewards" : ""
  },
  {
    "strName" : "CGEncContactPirate",
    "strInteraction" : "CGEncContactPirate",
    "fShipCashReward" : 0.0,
    "fStartATCRange" : 0.0,
    "strStartATC" : "",
    "strShipRewards" : ""
  },
  {
    "strName" : "CGEncFramedCaught",
    "strInteraction" : "CGEncFramedCaught",
    "fShipCashReward" : 0.0,
    "fStartATCRange" : 0.0,
    "strStartATC" : "",
    "strShipRewards" : ""
  },
  {
    "strName" : "CGEncFriendAdult",
    "strInteraction" : "CGEncFriendAdult",
    "fShipCashReward" : 0.0,
    "fStartATCRange" : 0.0,
    "strStartATC" : "",
    "strShipRewards" : ""
  },
  {
    "strName" : "CGEncInjury",
    "strInteraction" : "CGEncInjury",
    "fShipCashReward" : 0.0,
    "fStartATCRange" : 0.0,
    "strStartATC" : "",
    "strShipRewards" : ""
  },
  {
    "strName" : "CGEncManslaughter",
    "strInteraction" : "CGEncManslaughter",
    "fShipCashReward" : 0.0,
    "fStartATCRange" : 0.0,
    "strStartATC" : "",
    "strShipRewards" : ""
  },
  {
    "strName" : "CGEncShadyDealCaught",
    "strInteraction" : "CGEncShadyDealCaught",
    "fShipCashReward" : 0.0,
    "fStartATCRange" : 0.0,
    "strStartATC" : "",
    "strShipRewards" : ""
  },
  {
    "strName" : "CGEncShadyDealIntro",
    "strInteraction" : "CGEncShadyDealIntro",
    "fShipCashReward" : 0.0,
    "fStartATCRange" : 0.0,
    "strStartATC" : "",
    "strShipRewards" : ""
  },
  {
    "strName" : "CGEncShadyDealRefuse",
    "strInteraction" : "CGEncShadyDealRefuse",
    "fShipCashReward" : 0.0,
    "fStartATCRange" : 0.0,
    "strStartATC" : "",
    "strShipRewards" : ""
  },
  {
    "strName" : "CGEncShadyDealSuccess",
    "strInteraction" : "CGEncShadyDealSuccess",
    "fShipCashReward" : 4500.0,
    "fStartATCRange" : 0.0,
    "strStartATC" : "",
    "strShipRewards" : ""
  },
  {
    "strName" : "CGEncShipHulkSalvage",
    "strInteraction" : "CGEncShipHulkSalvage",
    "fShipCashReward" : 10000.0,
    "fStartATCRange" : 100.0,
    "strStartATC" : "OKLG",
    "strShipRewards" : "CGEncShipbreakerShips"
  },
  {
    "strName" : "CGEncShipPAX2020Intro",
    "strInteraction" : "CGEncShipPAX2020Intro",
    "fShipCashReward" : 0.0,
    "fStartATCRange" : 0.0,
    "strStartATC" : "",
    "strShipRewards" : ""
  },
  {
    "strName" : "CGEncShipPAX2020Take",
    "strInteraction" : "CGEncShipPAX2020Take",
    "fShipCashReward" : 0.0,
    "fStartATCRange" : 100.0,
    "strStartATC" : "OKLG",
    "strShipRewards" : "CGEncShipbreakerPAX2020Ships"
  },
  {
    "strName" : "CGEncShipSalvagePodIntro",
    "strInteraction" : "CGEncShipSalvagePodIntro",
    "fShipCashReward" : 0.0,
    "fStartATCRange" : 0.0,
    "strStartATC" : "",
    "strShipRewards" : ""
  },
  {
    "strName" : "CGEncShipMakeshiftSalvagePodIntro",
    "strInteraction" : "CGEncShipMakeshiftSalvagePodIntro",
    "fShipCashReward" : 0.0,
    "fStartATCRange" : 0.0,
    "strStartATC" : "",
    "strShipRewards" : ""
  },
  {
    "strName" : "CGEncShipSalvagePodTake",
    "strInteraction" : "CGEncShipSalvagePodTake",
    "fShipCashReward" : 0.0,
    "fStartATCRange" : 7.0,
    "strStartATC" : "OKLG",
    "strShipRewards" : "CGEncShipbreakerShips"
  },
  {
    "strName" : "CGEncShipSalvagePodCont",
    "strInteraction" : "CGEncShipSalvagePodCont",
    "fShipCashReward" : 0.0,
    "fStartATCRange" : 0.0,
    "strStartATC" : "",
    "strShipRewards" : ""
  },
  
  {
    "strName" : "CGEncRichSchmuckIntro",
    "strInteraction" : "CGEncRichSchmuckIntro",
    "fShipCashReward" : 0.0,
    "fStartATCRange" : 0.0,
    "strStartATC" : "",
    "strShipRewards" : ""
  },
  {
    "strName" : "CGEncRichSchmuckInciteRiot",
    "strInteraction" : "CGEncRichSchmuckInciteRiot",
    "fShipCashReward" : 0.0,
    "fStartATCRange" : 0.0,
    "strStartATC" : "",
    "strShipRewards" : ""
  },
  {
    "strName" : "CGEncRichSchmuckPickpocket",
    "strInteraction" : "CGEncRichSchmuckPickpocket",
    "fShipCashReward" : 450.0,
    "fStartATCRange" : 0.0,
    "strStartATC" : "",
    "strShipRewards" : ""
  },
  {
    "strName" : "CGEncRichSchmuckMug",
    "strInteraction" : "CGEncRichSchmuckMug",
    "fShipCashReward" : 0.0,
    "fStartATCRange" : 0.0,
    "strStartATC" : "",
    "strShipRewards" : ""
  },
  {
    "strName" : "CGEncRichSchmuckSeduce",
    "strInteraction" : "CGEncRichSchmuckSeduce",
    "fShipCashReward" : 1250.0,
    "fStartATCRange" : 0.0,
    "strStartATC" : "",
    "strShipRewards" : ""
  },
  {
    "strName" : "CGEncRichSchmuckCorpSecrets",
    "strInteraction" : "CGEncRichSchmuckCorpSecrets",
    "fShipCashReward" : 3400.0,
    "fStartATCRange" : 0.0,
    "strStartATC" : "",
    "strShipRewards" : ""
  },
  {
    "strName" : "CGEncRichSchmuckHackPhone",
    "strInteraction" : "CGEncRichSchmuckHackPhone",
    "fShipCashReward" : 2850.0,
    "fStartATCRange" : 0.0,
    "strStartATC" : "",
    "strShipRewards" : ""
  },
  {
    "strName" : "CGEncPodDisasterIntro",
    "strInteraction" : "CGEncPodDisasterIntro",
    "fShipCashReward" : 0.0,
    "fStartATCRange" : 0.0,
    "strStartATC" : "",
    "strShipRewards" : ""
  },
  {
    "strName" : "CGEncPodDisasterHackEngine",
    "strInteraction" : "CGEncPodDisasterHackEngine",
    "fShipCashReward" : 0.0,
    "fStartATCRange" : 0.0,
    "strStartATC" : "",
    "strShipRewards" : ""
  },
  {
    "strName" : "CGEncPodDisasterNavigate",
    "strInteraction" : "CGEncPodDisasterNavigate",
    "fShipCashReward" : 0.0,
    "fStartATCRange" : 0.0,
    "strStartATC" : "",
    "strShipRewards" : ""
  },
  {
    "strName" : "CGEncPodDisasterEngMechanical",
    "strInteraction" : "CGEncPodDisasterEngMechanical",
    "fShipCashReward" : 0.0,
    "fStartATCRange" : 0.0,
    "strStartATC" : "",
    "strShipRewards" : ""
  },
  {
    "strName" : "CGEncPodDisasterEngSpaceship",
    "strInteraction" : "CGEncPodDisasterEngSpaceship",
    "fShipCashReward" : 0.0,
    "fStartATCRange" : 0.0,
    "strStartATC" : "",
    "strShipRewards" : ""
  },
  {
    "strName" : "CGEncPodDisasterOpsEnvSuit",
    "strInteraction" : "CGEncPodDisasterOpsEnvSuit",
    "fShipCashReward" : 0.0,
    "fStartATCRange" : 0.0,
    "strStartATC" : "",
    "strShipRewards" : ""
  },
  {
    "strName" : "CGEncDailyGrindIntro",
    "strInteraction" : "CGEncDailyGrindIntro",
    "fShipCashReward" : 0.0,
    "fStartATCRange" : 0.0,
    "strStartATC" : "",
    "strShipRewards" : ""
  },
  {
    "strName" : "CGEncDailyGrindHacking",
    "strInteraction" : "CGEncDailyGrindHacking",
    "fShipCashReward" : 0.0,
    "fStartATCRange" : 0.0,
    "strStartATC" : "",
    "strShipRewards" : ""
  },
  {
    "strName" : "CGEncDailyGrindOldMovies",
    "strInteraction" : "CGEncDailyGrindOldMovies",
    "fShipCashReward" : 0.0,
    "fStartATCRange" : 0.0,
    "strStartATC" : "",
    "strShipRewards" : ""
  },
  {
    "strName" : "CGEncDailyGrindFeverishSuitMaintenance",
    "strInteraction" : "CGEncDailyGrindFeverishSuitMaintenance",
    "fShipCashReward" : 0.0,
    "fStartATCRange" : 0.0,
    "strStartATC" : "",
    "strShipRewards" : ""
  },
  {
    "strName" : "CGEncDailyGrindUndergroundBoxing",
    "strInteraction" : "CGEncDailyGrindUndergroundBoxing",
    "fShipCashReward" : 0.0,
    "fStartATCRange" : 0.0,
    "strStartATC" : "",
    "strShipRewards" : ""
  },
  {
    "strName" : "CGEncDailyGrindShippingNews",
    "strInteraction" : "CGEncDailyGrindShippingNews",
    "fShipCashReward" : 0.0,
    "fStartATCRange" : 0.0,
    "strStartATC" : "",
    "strShipRewards" : ""
  },
  {
    "strName" : "CGEncRareSalvageIntro",
    "strInteraction" : "CGEncRareSalvageIntro",
    "fShipCashReward" : 0.0,
    "fStartATCRange" : 0.0,
    "strStartATC" : "",
    "strShipRewards" : ""
  },
  {
    "strName" : "CGEncRareSalvageTellAyotimiwa",
    "strInteraction" : "CGEncRareSalvageTellAyotimiwa",
    "fShipCashReward" : 0.0,
    "fStartATCRange" : 0.0,
    "strStartATC" : "",
    "strShipRewards" : ""
  },
  {
    "strName" : "CGEncRareSalvageSmuggleItOffSite",
    "strInteraction" : "CGEncRareSalvageSmuggleItOffSite",
    "fShipCashReward" : 700.0,
    "fStartATCRange" : 0.0,
    "strStartATC" : "",
    "strShipRewards" : ""
  },
  {
    "strName" : "CGEncRareSalvageTakeItForYourself",
    "strInteraction" : "CGEncRareSalvageTakeItForYourself",
    "fShipCashReward" : 0.0,
    "fStartATCRange" : 0.0,
    "strStartATC" : "",
    "strShipRewards" : ""
  },
  {
    "strName" : "CGEncRareSalvageBribeBoss",
    "strInteraction" : "CGEncRareSalvageBribeBoss",
    "fShipCashReward" : 0.0,
    "fStartATCRange" : 0.0,
    "strStartATC" : "",
    "strShipRewards" : ""
  },
  {
    "strName" : "CGEncTestIntro",
    "strInteraction" : "CGEncTestIntro",
    "fShipCashReward" : 0.0,
    "fStartATCRange" : 0.0,
    "strStartATC" : "",
    "strShipRewards" : ""
  },
  {
    "strName" : "CGEncTestA",
    "strInteraction" : "CGEncTestA",
    "fShipCashReward" : 0.0,
    "fStartATCRange" : 0.0,
    "strStartATC" : "",
    "strShipRewards" : ""
  },
  {
    "strName" : "CGEncTestB",
    "strInteraction" : "CGEncTestB",
    "fShipCashReward" : 0.0,
    "fStartATCRange" : 0.0,
    "strStartATC" : "",
    "strShipRewards" : ""
  },
  {
    "strName" : "CGEncTestC",
    "strInteraction" : "CGEncTestC",
    "fShipCashReward" : 0.0,
    "fStartATCRange" : 0.0,
    "strStartATC" : "",
    "strShipRewards" : ""
  },
  {
    "strName" : "CGEncTestD",
    "strInteraction" : "CGEncTestD",
    "fShipCashReward" : 0.0,
    "fStartATCRange" : 0.0,
    "strStartATC" : "",
    "strShipRewards" : ""
  },
  {
    "strName" : "CGEncUprooted",
    "strInteraction" : "CGEncUprooted",
    "fShipCashReward" : 0.0,
    "fStartATCRange" : 0.0,
    "strStartATC" : "",
    "strShipRewards" : ""
  },
  {
    "strName" : "CGEncCrackdownIntro",
    "strInteraction" : "CGEncCrackdownIntro",
    "fShipCashReward" : 0.0,
    "fStartATCRange" : 0.0,
    "strStartATC" : "",
    "strShipRewards" : ""
  },
  {
    "strName" : "CGEncCrackdownVents",
    "strInteraction" : "CGEncCrackdownVents",
    "fShipCashReward" : 0.0,
    "fStartATCRange" : 0.0,
    "strStartATC" : "",
    "strShipRewards" : ""
  },
  {
    "strName" : "CGEncCrackdownBluff",
    "strInteraction" : "CGEncCrackdownBluff",
    "fShipCashReward" : 0.0,
    "fStartATCRange" : 0.0,
    "strStartATC" : "",
    "strShipRewards" : ""
  },
  {
    "strName" : "CGEncCrackdownNothingToHide",
    "strInteraction" : "CGEncCrackdownNothingToHide",
    "fShipCashReward" : 0.0,
    "fStartATCRange" : 0.0,
    "strStartATC" : "",
    "strShipRewards" : ""
  },
  {
    "strName" : "CGEncCrackdownFakeAPressureAlarm",
    "strInteraction" : "CGEncCrackdownFakeAPressureAlarm",
    "fShipCashReward" : 0.0,
    "fStartATCRange" : 0.0,
    "strStartATC" : "",
    "strShipRewards" : ""
  },
  {
    "strName" : "CGEncCrackdownBeAHero",
    "strInteraction" : "CGEncCrackdownBeAHero",
    "fShipCashReward" : 0.0,
    "fStartATCRange" : 0.0,
    "strStartATC" : "",
    "strShipRewards" : ""
  },
  {
    "strName" : "CGEncPokerGameIntro",
    "strInteraction" : "CGEncPokerGameIntro",
    "fShipCashReward" : 0.0,
    "fStartATCRange" : 0.0,
    "strStartATC" : "",
    "strShipRewards" : ""
  },
  {
    "strName" : "CGEncPokerGameTechnicality",
    "strInteraction" : "CGEncPokerGameTechnicality",
    "fShipCashReward" : 0.0,
    "fStartATCRange" : 0.0,
    "strStartATC" : "",
    "strShipRewards" : ""
  },
  {
    "strName" : "CGEncPokerGameCallBluff",
    "strInteraction" : "CGEncPokerGameCallBluff",
    "fShipCashReward" : 0.0,
    "fStartATCRange" : 0.0,
    "strStartATC" : "",
    "strShipRewards" : ""
  },
  {
    "strName" : "CGEncPokerGameFold",
    "strInteraction" : "CGEncPokerGameFold",
    "fShipCashReward" : 0.0,
    "fStartATCRange" : 0.0,
    "strStartATC" : "",
    "strShipRewards" : ""
  },
  {
    "strName" : "CGEncPokerGameAccuse",
    "strInteraction" : "CGEncPokerGameAccuse",
    "fShipCashReward" : 0.0,
    "fStartATCRange" : 0.0,
    "strStartATC" : "",
    "strShipRewards" : ""
  },
  {
    "strName" : "CGEncPokerGameCheat",
    "strInteraction" : "CGEncCrackdownBeAHero",
    "fShipCashReward" : 0.0,
    "fStartATCRange" : 0.0,
    "strStartATC" : "",
    "strShipRewards" : ""
  },
  {
    "strName" : "CGEncPokerGameYoink",
    "strInteraction" : "CGEncPokerGameYoink",
    "fShipCashReward" : 0.0,
    "fStartATCRange" : 0.0,
    "strStartATC" : "",
    "strShipRewards" : ""
  }
]